tmsg_formatter/__init__.py
tmsg_formatter/tmsg_formatter.py
tmsg_formatter-0.0.8.dist-info/LICENSE
tmsg_formatter-0.0.8.dist-info/METADATA
tmsg_formatter-0.0.8.dist-info/WHEEL
tmsg_formatter-0.0.8.dist-info/top_level.txt
tmsg_formatter-0.0.8.dist-info/RECORD
