Metadata-Version: 2.1
Name: tmsg-formatter
Version: 0.0.8
Summary: Asynchronous tbot message formatter.
Author-email: Azerof <azerof0670@gmail.com>
Classifier: Programming Language :: Python :: 3
Classifier: License :: OSI Approved :: MIT License
Classifier: Operating System :: OS Independent
Requires-Python: >=3.7
License-File: LICENSE
